punctuators/__init__.py
punctuators/collectors/__init__.py
punctuators/collectors/pcs_collector.py
punctuators/collectors/sbd_collector.py
punctuators/data/__init__.py
punctuators/data/infer_dataset.py
punctuators/models/__init__.py
punctuators/models/punc_cap_seg_model.py
punctuators/models/sbd_model.py
punctuators-0.0.7.dist-info/METADATA
punctuators-0.0.7.dist-info/WHEEL
punctuators-0.0.7.dist-info/top_level.txt
punctuators-0.0.7.dist-info/RECORD
