Metadata-Version: 2.1
Name: punctuators
Version: 0.0.7
Summary: Punctuators and such
Author: Shane
Author-email: shane.carroll@utsa.edu
Requires-Python: >=3.6
Requires-Dist: onnxruntime
Requires-Dist: torch (>=1.9)
Requires-Dist: sentencepiece
Requires-Dist: huggingface-hub
Requires-Dist: omegaconf
Requires-Dist: numpy
